[
    {
        "id": 1000,
        "title": "Перечень продаваемых узлов АВФ",
        "items": [
            {
                "id": 1001,
                "title": "Комплект деталей в сборе на захват на АВФ-1",
                "price": ""
            },
            {
                "id": 1002,
                "title": "Комплект деталей в сборе на захват на АВФ-1М.2",
                "price": ""
            },
            {
                "id": 1003,
                "title": "Рама направляющая металлоконструкция",
                "price": ""
            },
            {
                "id": 1004,
                "title": "Рама направляющая в сборе с каретками, оголовником",
                "price": ""
            },
            {
                "id": 1005,
                "title": "Каретка грузовая",
                "price": ""
            },
            {
                "id": 1006,
                "title": "Ролик в сборе на каретку грузовую",
                "price": ""
            },
            {
                "id": 1007,
                "title": "Каретка нижняя",
                "price": ""
            },
            {
                "id": 1008,
                "title": "Каретка гидроцилиндров",
                "price": ""
            },
            {
                "id": 1009,
                "title": "Оголовник",
                "price": ""
            },
            {
                "id": 1010,
                "title": "Укладчик верхний",
                "price": ""
            },
            {
                "id": 1011,
                "title": "Укладчик нижний",
                "price": ""
            },
            {
                "id": 1012,
                "title": "Вибропогружатель",
                "price": ""
            },
            {
                "id": 1013,
                "title": "Сменное оборудование для бурения лидирующих скважин к агрегатам АВФ-1 и машинам МС-1",
                "price": ""
            },
            {
                "id": 1014,
                "title": "Сменное оборудование для установки винтовых свай опор контактной сети к агрегатам АВФ-1 и машинам МС-1",
                "price": ""
            },
            {
                "id": 1015,
                "title": "Сменное оборудование для разрушения фундаментов опор контактной сети к агрегатам АВФ-1 и машинам МС-1  ",
                "price": ""
            },
            {
                "id": 1016,
                "title": "Пневмоударный рабочий орган",
                "price": ""
            }
        ]
    }
]
